{
  "id": "bir-güldün-emre-fel-ve-funktakl-1776375524998",
  "title": "Bir Güldün",
  "artist": "Emre Fel ve Funktakl",
  "lyrics": {
    "type": "synced",
    "text": "[00:11.69] Artık gizleme benden\n[00:13.93] Seviyorsun sen de benim gibi\n[00:16.49] Göster bak ben ezelden vurgun\n[00:20.35] Ah deliler gibi\n[00:21.84] Böyle, yangın içerden sarmış\n[00:25.87] Bak kül eder beni\n[00:27.48] Gönlüm tenhada kalmış\n[00:30.45] Bekler ah deliler gibi\n[00:32.96] Bir güldün beni beni geri döndürdün\n[00:37.56] Beni bulamaz derdim yine başa döndürdün\n[00:42.96] Bahçemde bir güldün beni geri döndürdün\n[00:48.76] Hayır olamaz derdim yine taşa döndürdün\n[01:17.53] Artık gizleme benden\n[01:20.30] Seviyorsun sen de benim gibi\n[01:22.54] Göster bak ben ezelden vurgun\n[01:26.55] Ah deliler gibi\n[01:28.14] Böyle, yangın içerden sarmış\n[01:32.08] Bak kül eder beni\n[01:33.74] Gönlüm tenhada kalmış\n[01:36.53] Bekler ah deliler gibi\n[01:39.24] Bir güldün beni beni geri döndürdün\n[01:44.00] Beni bulamaz derdim yine başa döndürdün\n[01:49.08] Bahçemde bir güldün beni geri döndürdün\n[01:55.08] Hayır olamaz derdim beni taşa döndürdün\n[02:23.83] Gizleme benden artık olanları yok gelemem yine bak ben ezelden sevdalarda\n[02:34.44] Savrulurum yine gönlüm eser deli yok bi' yol olmasın ah dönemem geri sevdalardan\n[02:45.52] Bir güldün beni beni geri döndürdün\n[02:50.32] Beni bulamaz derdim yine başa döndürdün\n[02:55.49] Bahçemde bir güldün beni geri döndürdün\n[03:01.01] Hayır olamaz derdim yine taşa döndürdün\n[03:12.74]"
  },
  "uploadedAt": "2026-04-16T21:38:44.998Z",
  "audio": "https://res.cloudinary.com/dkhuq9o1h/video/upload/v1776375527/dunyamiz/music/kuycahupr7znfg4inxuf.mp3",
  "cover": "https://res.cloudinary.com/dkhuq9o1h/image/upload/v1776375528/dunyamiz/covers/nmvlsywgsph5jgtfotnl.jpg"
}